LICENSE.txt
README.md
setup.py
fablab_lib/__init__.py
fablab_lib.egg-info/PKG-INFO
fablab_lib.egg-info/SOURCES.txt
fablab_lib.egg-info/dependency_links.txt
fablab_lib.egg-info/requires.txt
fablab_lib.egg-info/top_level.txt
fablab_lib/Broker/__init__.py
fablab_lib/Broker/JsonPayload/__init__.py
fablab_lib/Broker/JsonPayload/function.py
fablab_lib/Broker/MQTT/__init__.py
fablab_lib/Broker/MQTT/function.py
fablab_lib/Broker/MQTT/paho/__init__.py
fablab_lib/Broker/MQTT/paho/mqtt/__init__.py
fablab_lib/Broker/MQTT/paho/mqtt/client.py
fablab_lib/Broker/MQTT/paho/mqtt/enums.py
fablab_lib/Broker/MQTT/paho/mqtt/matcher.py
fablab_lib/Broker/MQTT/paho/mqtt/packettypes.py
fablab_lib/Broker/MQTT/paho/mqtt/properties.py
fablab_lib/Broker/MQTT/paho/mqtt/publish.py
fablab_lib/Broker/MQTT/paho/mqtt/reasoncodes.py
fablab_lib/Broker/MQTT/paho/mqtt/subscribe.py
fablab_lib/Broker/MQTT/paho/mqtt/subscribeoptions.py
fablab_lib/Broker/SparkPlugB/__init__.py
fablab_lib/Broker/SparkPlugB/function.py
fablab_lib/Broker/SparkPlugB/mqtt_spb_wrapper/__init__.py
fablab_lib/Broker/SparkPlugB/mqtt_spb_wrapper/mqtt_spb_wrapper.py
fablab_lib/Broker/SparkPlugB/mqtt_spb_wrapper/paho/__init__.py
fablab_lib/Broker/SparkPlugB/mqtt_spb_wrapper/paho/mqtt/__init__.py
fablab_lib/Broker/SparkPlugB/mqtt_spb_wrapper/paho/mqtt/client.py
fablab_lib/Broker/SparkPlugB/mqtt_spb_wrapper/paho/mqtt/enums.py
fablab_lib/Broker/SparkPlugB/mqtt_spb_wrapper/paho/mqtt/matcher.py
fablab_lib/Broker/SparkPlugB/mqtt_spb_wrapper/paho/mqtt/packettypes.py
fablab_lib/Broker/SparkPlugB/mqtt_spb_wrapper/paho/mqtt/properties.py
fablab_lib/Broker/SparkPlugB/mqtt_spb_wrapper/paho/mqtt/publish.py
fablab_lib/Broker/SparkPlugB/mqtt_spb_wrapper/paho/mqtt/reasoncodes.py
fablab_lib/Broker/SparkPlugB/mqtt_spb_wrapper/paho/mqtt/subscribe.py
fablab_lib/Broker/SparkPlugB/mqtt_spb_wrapper/paho/mqtt/subscribeoptions.py
fablab_lib/Broker/SparkPlugB/mqtt_spb_wrapper/spb_core/__init__.py
fablab_lib/Broker/SparkPlugB/mqtt_spb_wrapper/spb_core/sparkplug_b.py
fablab_lib/Broker/SparkPlugB/mqtt_spb_wrapper/spb_core/sparkplug_b_pb2.py
fablab_lib/Broker/SparkPlugB/mqtt_spb_wrapper/spb_core/sparkplug_b_tools.py
