Metadata-Version: 2.1
Name: fablab-lib
Version: 0.2.5
Summary: A package for communicating with PLC via industrial protocols such as OPC UA, Modbus, etc.         and logging data to a CSV file.
Home-page: https://github.com/78-quangSky/MyPackage
Author: FabLab Innovation
Author-email: thien.dangquang.sistrain@gmail.com
License: MIT
Classifier: License :: OSI Approved :: MIT License
Classifier: Programming Language :: Python :: 3.7
Classifier: Operating System :: OS Independent
Requires-Python: >=3.7
License-File: LICENSE.txt
